Workbook

Sheet Base_Vendas
A1: ID Pedido | B1: Data | C1: Categoria | D1: Faturamento Bruto | E1: Custo Produto (CMV) | F1: Custo Marketing (CAC) | G1: Lucro Líquido | H1: Margem de Lucro | I1: ROI Mkt
A2: PED-1000 | B2: 2026-01-01 | C2: Vestuário | D2: 203.82 | E2: 82.95 | F2: 39.96 | G2: =D2-E2-F2 -> 80.91 | H2: =IFERROR(G2/D2,0) -> 0.39696791 | I2: =IFERROR(G2/F2,0) -> 2.0247748
A3: PED-1001 | B3: 2026-01-02 | C3: Beleza | D3: 259.61 | E3: 84.92 | F3: 51.76 | G3: =D3-E3-F3 -> 122.93 | H3: =IFERROR(G3/D3,0) -> 0.47351797 | I3: =IFERROR(G3/F3,0) -> 2.375
A4: PED-1002 | B4: 2026-01-03 | C4: Casa & Decoração | D4: 927.28 | E4: 430.38 | F4: 94.61 | G4: =D4-E4-F4 -> 402.29 | H4: =IFERROR(G4/D4,0) -> 0.43383875 | I4: =IFERROR(G4/F4,0) -> 4.2520875
A5: PED-1003 | B5: 2026-01-04 | C5: Vestuário | D5: 198.55 | E5: 60.5 | F5: 36.46 | G5: =D5-E5-F5 -> 101.59 | H5: =IFERROR(G5/D5,0) -> 0.51165953 | I5: =IFERROR(G5/F5,0) -> 2.7863412
A6: PED-1004 | B6: 2026-01-05 | C6: Eletrônicos | D6: 1648.76 | E6: 1155.55 | F6: 236.65 | G6: =D6-E6-F6 -> 256.56 | H6: =IFERROR(G6/D6,0) -> 0.15560785 | I6: =IFERROR(G6/F6,0) -> 1.0841327
A7: PED-1005 | B7: 2026-01-06 | C7: Eletrônicos | D7: 1473.09 | E7: 1017.96 | F7: 195.76 | G7: =D7-E7-F7 -> 259.37 | H7: =IFERROR(G7/D7,0) -> 0.17607207 | I7: =IFERROR(G7/F7,0) -> 1.3249387
A8: PED-1006 | B8: 2026-01-07 | C8: Eletrônicos | D8: 1417.76 | E8: 932.46 | F8: 142.18 | G8: =D8-E8-F8 -> 343.12 | H8: =IFERROR(G8/D8,0) -> 0.24201557 | I8: =IFERROR(G8/F8,0) -> 2.4132789
A9: PED-1007 | B9: 2026-01-08 | C9: Beleza | D9: 131.59 | E9: 45.13 | F9: 30.37 | G9: =D9-E9-F9 -> 56.09 | H9: =IFERROR(G9/D9,0) -> 0.4262482 | I9: =IFERROR(G9/F9,0) -> 1.8468884
A10: PED-1008 | B10: 2026-01-09 | C10: Casa & Decoração | D10: 1060.08 | E10: 562.6 | F10: 174.16 | G10: =D10-E10-F10 -> 323.32 | H10: =IFERROR(G10/D10,0) -> 0.30499585 | I10: =IFERROR(G10/F10,0) -> 1.8564538
A11: PED-1009 | B11: 2026-01-10 | C11: Casa & Decoração | D11: 523.88 | E11: 279.69 | F11: 74.99 | G11: =D11-E11-F11 -> 169.2 | H11: =IFERROR(G11/D11,0) -> 0.32297473 | I11: =IFERROR(G11/F11,0) -> 2.2563008
A12: PED-1010 | B12: 2026-01-11 | C12: Eletrônicos | D12: 2980.09 | E12: 2204.1 | F12: 304.74 | G12: =D12-E12-F12 -> 471.25 | H12: =IFERROR(G12/D12,0) -> 0.15813281 | I12: =IFERROR(G12/F12,0) -> 1.5464002
A13: PED-1011 | B13: 2026-01-12 | C13: Beleza | D13: 115.22 | E13: 31.43 | F13: 22.2 | G13: =D13-E13-F13 -> 61.59 | H13: =IFERROR(G13/D13,0) -> 0.53454261 | I13: =IFERROR(G13/F13,0) -> 2.7743243
... A91: PED-1089 | B91: 2026-03-31 | C91: Vestuário | D91: 413.6 | E91: 182.41 | F91: 73.43 | G91: =D91-E91-F91 -> 157.76 | H91: =IFERROR(G91/D91,0) -> 0.38143133 | I91: =IFERROR(G91/F91,0) -> 2.1484407

Sheet Dashboard_Comercial
B1: E-COMMERCE BUSINESS INTELLIGENCE - VISÃO CONSOLIDADA
B2: Faturamento Total | E2: Volume de Vendas | H2: Ticket Médio | K2: Lucro Líquido Real
B3: =SUM(Base_Vendas!D:D) -> 80786.67 | E3: =COUNTA(Base_Vendas!A:A)-1 -> 90 | H3: =AVERAGE(Base_Vendas!D:D) -> 897.62967 | K3: =SUM(Base_Vendas!G:G) -> 21899.66
B7: Análise de Performance por Categoria
B8: Categoria | C8: Faturamento | D8: Lucro | E8: Margem Média | F8: ROI
B9: Eletrônicos | C9: =SUMIFS(Base_Vendas!D:D, Base_Vendas!C:C, "Eletrônicos") -> 52057.35 | D9: =SUMIFS(Base_Vendas!G:G, Base_Vendas!C:C, "Eletrônicos") -> 9378.96 | E9: =IFERROR(D9/C9, 0) -> 0.18016591 | F9: =AVERAGEIFS(Base_Vendas!I:I, Base_Vendas!C:C, "Eletrônicos") -> 1.5843868
B10: Vestuário | C10: =SUMIFS(Base_Vendas!D:D, Base_Vendas!C:C, "Vestuário") -> 11453.95 | D10: =SUMIFS(Base_Vendas!G:G, Base_Vendas!C:C, "Vestuário") -> 5199.7 | E10: =IFERROR(D10/C10, 0) -> 0.45396566 | F10: =AVERAGEIFS(Base_Vendas!I:I, Base_Vendas!C:C, "Vestuário") -> 2.8490012
B11: Casa & Decoração | C11: =SUMIFS(Base_Vendas!D:D, Base_Vendas!C:C, "Casa & Decoração") -> 13109.44 | D11: =SUMIFS(Base_Vendas!G:G, Base_Vendas!C:C, "Casa & Decoração") -> 5316.39 | E11: =IFERROR(D11/C11, 0) -> 0.40553906 | F11: =AVERAGEIFS(Base_Vendas!I:I, Base_Vendas!C:C, "Casa & Decoração") -> 3.111318
B12: Beleza | C12: =SUMIFS(Base_Vendas!D:D, Base_Vendas!C:C, "Beleza") -> 4165.93 | D12: =SUMIFS(Base_Vendas!G:G, Base_Vendas!C:C, "Beleza") -> 2004.61 | E12: =IFERROR(D12/C12, 0) -> 0.48119147 | F12: =AVERAGEIFS(Base_Vendas!I:I, Base_Vendas!C:C, "Beleza") -> 2.5550473
